sipua/__init__.py
sipua/application.py
sipua/call.py
sipua/dialog.py
sipua/py.typed
sipua/transaction.py
sipua/transport.py
sipua/utils.py
sipua-0.5.4.dist-info/licenses/LICENSE
sipua-0.5.4.dist-info/METADATA
sipua-0.5.4.dist-info/WHEEL
sipua-0.5.4.dist-info/top_level.txt
sipua-0.5.4.dist-info/RECORD
