Metadata-Version: 2.4
Name: sipua
Version: 0.5.4
Summary: Pure python SIP user agent
Author-email: Spacinov Engineering <opensource@spacinov.com>
License-Expression: BSD-2-Clause
Project-URL: Documentation, https://sipua.readthedocs.io/
Project-URL: Repository, https://github.com/spacinov/sipua
Project-URL: Issues, https://github.com/spacinov/sipua/issues
Keywords: SIP,RFC3261
Classifier: Development Status :: 3 - Alpha
Classifier: Intended Audience :: Developers
Classifier: Intended Audience :: System Administrators
Classifier: Intended Audience :: Telecommunications Industry
Classifier: Operating System :: OS Independent
Classifier: Programming Language :: Python :: 3.10
Classifier: Programming Language :: Python :: 3.11
Classifier: Programming Language :: Python :: 3.12
Classifier: Programming Language :: Python :: 3.13
Classifier: Topic :: Communications :: Telephony
Classifier: Typing :: Typed
Requires-Python: >=3.10
License-File: LICENSE
Requires-Dist: aiortc<1.15,>=1.13
Requires-Dist: sipmessage<0.7.0,>=0.6.2
Requires-Dist: websockets<16,>=15
Provides-Extra: dev
Requires-Dist: check-manifest; extra == "dev"
Requires-Dist: coverage; extra == "dev"
Requires-Dist: mypy; extra == "dev"
Requires-Dist: pyroma; extra == "dev"
Requires-Dist: ruff; extra == "dev"
Dynamic: license-file
